lib_dzne_overload/__init__.py
lib_dzne_overload/tests/__init__.py
lib_dzne_overload/tests/test_1984.py
lib_dzne_overload-0.2.3.dist-info/LICENSE.txt
lib_dzne_overload-0.2.3.dist-info/METADATA
lib_dzne_overload-0.2.3.dist-info/WHEEL
lib_dzne_overload-0.2.3.dist-info/top_level.txt
lib_dzne_overload-0.2.3.dist-info/RECORD
