Metadata-Version: 2.1
Name: lib_dzne_overload
Version: 0.2.3
Summary: Library for overloading functions.
Author-email: Johannes <johannes-programming@mailfence.com>, Johannes <johannes-programming@posteo.org>
License: The MIT License (MIT)
Project-URL: Documentation, https://pypi.org/project/lib_dzne_overload
Project-URL: Download, https://pypi.org/project/lib-dzne-overload/#files
Project-URL: Source, https://github.com/johannes-programming/lib_dzne_overload
Classifier: Development Status :: 3 - Alpha
Classifier: License :: OSI Approved :: MIT License
Classifier: Programming Language :: Python
Classifier: Programming Language :: Python :: 3
Classifier: Programming Language :: Python :: 3 :: Only
Requires-Python: >=3.11
License-File: LICENSE.txt
